breach_buster/__init__.py
breach_buster/examples/__init__.py
breach_buster/examples/demo_server.py
breach_buster/middleware/__init__.py
breach_buster/middleware/gzip.py
breach_buster_redux-0.1.1.dist-info/DESCRIPTION.rst
breach_buster_redux-0.1.1.dist-info/METADATA
breach_buster_redux-0.1.1.dist-info/RECORD
breach_buster_redux-0.1.1.dist-info/WHEEL
breach_buster_redux-0.1.1.dist-info/metadata.json
breach_buster_redux-0.1.1.dist-info/top_level.txt
breach_buster_redux-0.1.1.dist-info/zip-safe
