Metadata-Version: 2.0
Name: breach-buster-redux
Version: 0.1.1
Summary: BREACH resistant gzip middleware for Django
Home-page: https://github.com/miki725/breach_buster
Author: Miroslav Shubernetskiy
Author-email: UNKNOWN
License: GPLv3
Platform: UNKNOWN
Requires-Dist: django
Requires-Dist: six
